[
  {
    "_id": 1,
    "username": "meiaagent@lightwitch.org",
    "password": "Grupo3isbest",
    "isManager": false
  },
  {
    "_id": 2,
    "username": "meiaagent1@lightwitch.org",
    "password": "Grupo3isbest",
    "isManager": false
  },
  {
    "_id": 3,
    "username": "meiaagent2@lightwitch.org",
    "password": "Grupo3isbest",
    "isManager": true
  },
  {
    "_id": 4,
    "username": "meiaagent3@lightwitch.org",
    "password": "Grupo3isbest",
    "isManager": false
  },
  {
    "_id": 5,
    "username": "meiaagent4@lightwitch.org",
    "password": "Grupo3isbest",
    "isManager": false
  },
  {
    "_id": 6,
    "username": "meiaagent5@lightwitch.org",
    "password": "Grupo3isbest",
    "isManager": false
  },
  {
    "_id": 7,
    "username": "meiaagent6@lightwitch.org",
    "password": "Grupo3isbest",
    "isManager": false
  }
]